{
  "id": "shipping-guide",
  "title": "配送ガイド",
  "version": "1.0",
  "effectiveDate": "2026-04-01",
  "ownerDepartment": "ロジスティクス",
  "summary": "送料・お届け日数・日時指定・追跡の確認方法を案内します。",
  "sections": [
    {
      "id": "shipping-fee",
      "title": "送料",
      "articleNumber": "1",
      "body": "本州宛は税込5,000円以上のご注文で送料無料です。5,000円未満は送料550円（税込）です。北海道・沖縄・離島は追加送料がかかる場合があります。大型商品は別途案内します。"
    },
    {
      "id": "delivery-estimate",
      "title": "お届け日数目安",
      "articleNumber": "2",
      "body": "在庫がある商品はご注文確定後、2〜4営業日で発送します。東京宛は発送後1〜2日程度が目安です。離島・一部地域は追加で1〜3日かかることがあります。予約・取り寄せ品は商品ページの予定に従います。"
    },
    {
      "id": "datetime-specify",
      "title": "日時指定",
      "articleNumber": "3",
      "body": "配送業者の対応地域では日時指定が可能です。指定可能な時間帯はチェックアウト画面でご確認ください。指定締切は出荷準備開始前までです。"
    },
    {
      "id": "how-to-track",
      "title": "配送状況の確認方法",
      "articleNumber": "4",
      "body": "出荷後はマイページの注文詳細、または出荷完了メールの追跡番号から状況を確認できます。個別注文の現在地をチャットで知るには注文番号が必要です。例: TW-20482。本ガイドだけでは特定注文の位置は分かりません。"
    },
    {
      "id": "redelivery",
      "title": "再配達・不在",
      "articleNumber": "5",
      "body": "不在票が届いた場合は配送業者の案内に従い再配達を依頼してください。保管期限を過ぎた場合は当社から再送手続きのご案内をします。"
    }
  ]
}
